{
  "version": "7",
  "dialect": "postgresql",
  "entries": [
    {
      "idx": 0,
      "version": "7",
      "when": 1767297420288,
      "tag": "0000_add_team_pages_media_activity",
      "breakpoints": true
    },
    {
      "idx": 1,
      "version": "7",
      "when": 1767359003563,
      "tag": "0001_add_influencer_role",
      "breakpoints": true
    },
    {
      "idx": 2,
      "version": "7",
      "when": 1735833600000,
      "tag": "0002_add_payment_providers",
      "breakpoints": true
    },
    {
      "idx": 3,
      "version": "7",
      "when": 1767453033320,
      "tag": "0003_first_mystique",
      "breakpoints": true
    },
    {
      "idx": 4,
      "version": "7",
      "when": 1767454242754,
      "tag": "0004_aromatic_terrax",
      "breakpoints": true
    },
    {
      "idx": 5,
      "version": "7",
      "when": 1767466997994,
      "tag": "0005_clammy_medusa",
      "breakpoints": true
    },
    {
      "idx": 6,
      "version": "7",
      "when": 1767524938741,
      "tag": "0006_add_gift_product_discount_type",
      "breakpoints": true
    }
  ]
}